blacksheep/__init__.py
blacksheep/_constants.py
blacksheep/_outlierTable.py
blacksheep/catheat.py
blacksheep/classes.py
blacksheep/cli.py
blacksheep/comparisons.py
blacksheep/deva.py
blacksheep/parsers.py
blacksheep/simulate.py
blacksheep/visualization.py
blksheep-0.0.7.dist-info/LICENSE
blksheep-0.0.7.dist-info/METADATA
blksheep-0.0.7.dist-info/WHEEL
blksheep-0.0.7.dist-info/entry_points.txt
blksheep-0.0.7.dist-info/top_level.txt
blksheep-0.0.7.dist-info/RECORD
