Metadata-Version: 2.1
Name: blksheep
Version: 0.0.7
Summary: A package for differential extreme values analysis
Home-page: https://github.com/ruggleslab/blackSheep/
Author: Ruggles Lab
Author-email: ruggleslab@gmail.com
License: UNKNOWN
Platform: UNKNOWN
Classifier: Programming Language :: Python :: 3.7
Classifier: License :: OSI Approved :: MIT License
Classifier: Operating System :: MacOS
Classifier: Operating System :: Unix
Requires-Dist: matplotlib (>=3.3.4)
Requires-Dist: numpy (>=1.20.1)
Requires-Dist: pandas (>=1.2.2)
Requires-Dist: scipy (>=1.6.0)
Requires-Dist: seaborn (>=0.11.1)
Requires-Dist: statsmodels (>=0.12.2)
